blocktrix/__init__.py
blocktrix/solver_bcyclic.py
blocktrix/solver_thomas.py
blocktrix/utils.py
blocktrix-0.0.5.dist-info/licenses/LICENSE
blocktrix-0.0.5.dist-info/METADATA
blocktrix-0.0.5.dist-info/WHEEL
blocktrix-0.0.5.dist-info/top_level.txt
blocktrix-0.0.5.dist-info/RECORD
