Metadata-Version: 2.4
Name: blocktrix
Version: 0.0.5
Summary: A JAX library for solving block tri-diagonal matrix systems
Author-email: Philip Mocz <philip.mocz@gmail.com>
License-Expression: Apache-2.0
Project-URL: Documentation, https://github.com/pmocz/blocktrix
Project-URL: Homepage, https://github.com/pmocz/blocktrix
Requires-Python: >=3.11
License-File: LICENSE
Requires-Dist: jax==0.6.0
Provides-Extra: dev
Requires-Dist: ruff; extra == "dev"
Requires-Dist: pytest; extra == "dev"
Requires-Dist: pytest-cov; extra == "dev"
Requires-Dist: coverage-badge; extra == "dev"
Requires-Dist: sphinx-lint>=1.0.0; extra == "dev"
Requires-Dist: typos; extra == "dev"
Provides-Extra: cuda12
Requires-Dist: jax[cuda12]==0.6.0; extra == "cuda12"
Dynamic: license-file
